cairn_geographics/__init__.py
cairn_geographics/connection.py
cairn_geographics/gis_object.py
cairn_geographics/location.py
cairn_geographics/measure.py
cairn_geographics/region.py
cairn_geographics/type_factory.py
cairn_geographics-0.4.0.dist-info/DESCRIPTION.rst
cairn_geographics-0.4.0.dist-info/METADATA
cairn_geographics-0.4.0.dist-info/RECORD
cairn_geographics-0.4.0.dist-info/WHEEL
cairn_geographics-0.4.0.dist-info/metadata.json
cairn_geographics-0.4.0.dist-info/top_level.txt
