Metadata-Version: 2.0
Name: cairn-geographics
Version: 0.4.0
Summary: Client library for Cairn Geographics library.
Home-page: http://www.cairngeographics.com
Author: Cairn Labs, LLC
Author-email: sam@cairnlabs.com
License: MIT
Keywords: geography census data gis road distance driving time osm
Platform: UNKNOWN
Requires-Dist: requests
Requires-Dist: pytest
Requires-Dist: urllib3
